pillar_tool/__init__.py
pillar_tool/cli.py
pillar_tool/defaults.py
pillar_tool/format.py
pillar_tool/pillar.py
pillar_tool-0.2.0.dist-info/WHEEL
pillar_tool-0.2.0.dist-info/entry_points.txt
pillar_tool-0.2.0.dist-info/METADATA
pillar_tool-0.2.0.dist-info/RECORD
